src/__init__.py
src/JsonLibralyCreator/__init__.py
src/JsonLibralyCreator/main.py
JsonCreatoor-0.0.1.dist-info/METADATA
JsonCreatoor-0.0.1.dist-info/WHEEL
JsonCreatoor-0.0.1.dist-info/top_level.txt
JsonCreatoor-0.0.1.dist-info/RECORD
