Metadata-Version: 2.1
Name: JsonCreatoor
Version: 0.0.1
Summary: Json library creator
Author: Gennadiy
Author-email: genkaprostotak@gmail.com
Classifier: Programming Language :: Python :: 3
Classifier: License :: OSI Approved :: MIT License
Classifier: Operating System :: OS Independent
Requires-Python: >=3.10.0
Requires-Dist: hatchling
